[
  
  {
    "definitions": [
      {
        "word": "exhaust",
        "phonetics": "/ɪɡˈzɑːst/",
        "partOfSpeech": "verb",
        "enDefinition": "to make someone extremely tired",
        "ptDefinition": "fazer alguém ficar extremamente cansado; exaurir, esgotar",
        "examples": [
          {
            "enExample": "The long journey exhausted the children.",
            "ptExample": "A longa viagem exauriu as crianças."
          }
        ],
        "synonyms": ["tire out", "wear out", "fatigue"],
        "antonyms": ["energize", "refresh", "invigorate"],
        "seeAlso": ["drain", "deplete"],
        "notes": [
          {
            "enNote": "Often used to describe a state of extreme physical or mental fatigue.",
            "ptNote": "Frequentemente usado para descrever um estado de fadiga física ou mental extrema."
          }
        ]
      },
      {
        "word": "exhausted",
        "phonetics": "/ɪɡˈzɑːstɪd/",
        "partOfSpeech": "adjective",
        "enDefinition": "extremely tired",
        "ptDefinition": "extremamente cansado",
        "examples": [
          {
            "enExample": "After the marathon, she was completely exhausted.",
            "ptExample": "Depois da maratona, ela estava completamente exausta."
          },
          {
            "enExample": "He felt exhausted after working all night.",
            "ptExample": "Ele se sentiu exausto depois de trabalhar a noite toda."
          }
        ],
        "synonyms": ["tired", "fatigued", "worn out"],
        "antonyms": ["energetic", "rested", "refreshed"],
        "seeAlso": ["weary", "drained"]
      }
    ]
  },
  {
    "definitions": [
      {
        "word": "anxious",
        "phonetics": "/ˈæŋk.ʃəs/",
        "partOfSpeech": "adjective",
        "enDefinition": "feeling or showing worry, nervousness, or unease about something with an uncertain outcome",
        "ptDefinition": "sentindo ou mostrando preocupação, nervosismo ou inquietação sobre algo com um resultado incerto",
        "examples": [
          {
            "enExample": "She was anxious about the exam results.",
            "ptExample": "Ela estava ansiosa com os resultados do exame."
          },
          {
            "enExample": "He felt anxious before the job interview.",
            "ptExample": "Ele se sentiu ansioso antes da entrevista de emprego."
          }
        ],
        "synonyms": ["worried", "nervous", "uneasy", "apprehensive"],
        "antonyms": ["calm", "relaxed", "confident"],
        "seeAlso": ["nervous", "apprehensive"],
        "notes": [
          {
            "enNote": "Often used to describe a state of mental unease or worry.",
            "ptNote": "Frequentemente usado para descrever um estado de inquietação ou preocupação mental."
          }
        ]
      }
    ]
  },
  {
    "definitions": [
      {
        "word": "eating one's lunch",
        "partOfSpeech": "idiom",
        "enDefinition": "to outperform or take advantage of someone, often in a competitive or business context",
        "ptDefinition": "superar ou tirar vantagem de alguém, geralmente em um contexto competitivo ou de negócios",
        "examples": [
          {
            "enExample": "Their competitor is eating their lunch by offering lower prices and better customer service.",
            "ptExample": "O concorrente está superando eles oferecendo preços mais baixos e um atendimento ao cliente melhor."
          },
          {
            "enExample": "If we don’t innovate, smaller companies will start eating our lunch in this market.",
            "ptExample": "Se não inovarmos, empresas menores vão começar a nos superar neste mercado."
          }
        ],
        "synonyms": ["outperform", "surpass", "dominate"],
        "antonyms": ["fall behind", "ose to", "be outdone"]
      }
    ]
  },
  {
    "definitions": [
      {
        "word": "educated guess",
        "partOfSpeech": "noun",
        "enDefinition": "a guess based on knowledge and experience, rather than a random guess",
        "ptDefinition": "um palpite baseado em conhecimento e experiência, em vez de um palpite aleatório; suposição",
        "examples": [
          {
            "enExample": "After reviewing the data, I made an educated guess about the company's future growth.",
            "ptExample": "Após revisar os dados, fiz uma suposição sobre o crescimento futuro da empresa."
          }
        ],
        "synonyms": ["informed guess", "reasoned guess"],
        "antonyms": ["wild guess", "shot in the dark"],
        "seeAlso": ["hypothesis"]
      }
    ]
  },
  {
    "definitions": [
      {
        "word": "escarole",
        "phonetics": "/ˈes.kə.roʊl/",
        "partOfSpeech": "noun",
        "enDefinition": "a type of endive or chicory (= a plant with a slightly bitter taste that is eaten uncooked in salads or as a vegetable) with wide, curly green leaves",
        "ptDefinition": "um tipo de chicória ou endívia com folhas verdes largas e encaracoladas",
        "examples": [
          {
            "enExample": "Add a drained can of chickpeas and the coarsely chopped escarole.",
            "ptExample": "Adicione uma lata de grão-de-bico escorrida e a escarola bem picada (grosseiramente)."
          }
        ]
      }
    ]
  },
  {
    "definitions": [
      {
        "word": "ethical",
        "phonetics": "/ˈeθ.ɪ.kəl/",
        "partOfSpeech": "adjective",
        "enDefinition": "relating to beliefs about what is morally right and wrong",
        "ptDefinition": "ético",
        "examples": [
          {
            "enExample": "Ensuring patient confidentiality is an essential aspect of ethical practice in the medical profession.",
            "ptExample": "Assegurar / Garantir a confidencialidade do paciente é uma parte fundamental da conduta ética na medicina."
          }
        ],
        "synonyms": ["honest", "honoroble", "humane", "proper"],
        "antonyms": ["dishonest", "immoral", "corrupt", "improper", "unjust"]
      }
    ]
  },
  {
    "definitions": [
      {
        "word": "everyone",
        "phonetics": "ˈɛvrɪwʌn",
        "partOfSpeech": "pronoun",
        "enDefinition": "Every person; all people.",
        "ptDefinition": "Toda pessoa; todas as pessoas.",
        "examples": [
          {
            "enExample": "Everyone is invited to the party.",
            "ptExample": "Todos estão convidados para a festa."
          },
          {
            "enExample": "Everyone agreed with the decision.",
            "ptExample": "Todos concordaram com a decisão."
          }
        ],
        "synonyms": ["everybody", "all"],
        "antonyms": ["nobody", "no one"],
        "seeAlso": ["all", "anyone", "somebody"],
        "notes": [
          {
            "enNote": "Used to refer to all individuals collectively.",
            "ptNote": "Usado para se referir a todas as pessoas coletivamente."
          }
        ]
      }
    ]
  },
  {
    "definitions": [
      {
        "word": "excite",
        "phonetics": "/ɪkˈsaɪt/",
        "partOfSpeech": "verb",
        "enDefinition": "to cause someone to feel very enthusiastic and eager",
        "ptDefinition": "causar em alguém um sentimento de muito entusiasmo e animação",
        "examples": [
          {
            "enExample": "The news of the concert excited her.",
            "ptExample": "A notícia do show a animou."
          },
          {
            "enExample": "The discovery excited the scientific community.",
            "ptExample": "A descoberta entusiasmou a comunidade científica."
          }
        ],
        "synonyms": ["thrill", "elate", "stimulate", "energize"],
        "antonyms": ["bore", "depress", "calm", "discourage"],
        "seeAlso": ["arouse", "inspire", "provoke"]
      }
    ]
  }
]
